gtemptsi.py
gtemptsi-0.0.2.dist-info/METADATA
gtemptsi-0.0.2.dist-info/WHEEL
gtemptsi-0.0.2.dist-info/entry_points.txt
gtemptsi-0.0.2.dist-info/top_level.txt
gtemptsi-0.0.2.dist-info/RECORD
