Metadata-Version: 2.1
Name: gtemptsi
Version: 0.0.2
Summary: A package for displaying global temperature and co2
Home-page: https://github.com/y-takefuji/gtemptsi
Author: yoshiyasu takefuji
Author-email: takefuji@keio.jp
Project-URL: Bug Tracker, https://github.com/y-takefuji/gtemptsi
Classifier: Programming Language :: Python :: 3
Classifier: License :: OSI Approved :: MIT License
Classifier: Operating System :: OS Independent
Requires-Python: >=3.8
